Workbook

Sheet Read me
A1: National AI strategy budget: Example Republic (fictional)
A2: ILLUSTRATIVE: example figures for a fictional country. Replace with your own costing.
A3: Currency: USD. Years: Y1, Y2, Y3, Y4, Y5.
A4: Type numbers only on 'Line items' and 'Financing shares'. Every other sheet is formulas.
A5: Compute lines come from planner/compute_planner.py (see the planner assumptions).
A6: Book: National AI Strategy in Practice, Chapter 10. Licence: MIT.

Sheet Line items
A1: Pillar | B1: Item | C1: Basis | D1: Y1 | E1: Y2 | F1: Y3 | G1: Y4 | H1: Y5 | I1: Total
A2: Governance and delivery unit | B2: Delivery unit (15 staff) | C2: 15 x $40k loaded | D2: 600000 | E2: 600000 | F2: 600000 | G2: 600000 | H2: 600000 | I2: =SUM(D2:H2)
A3: Governance and delivery unit | B3: Steering committee and coordination | C3: Secretariat, meetings | D3: 100000 | E3: 100000 | F3: 100000 | G3: 100000 | H3: 100000 | I3: =SUM(D3:H3)
A4: Compute | B4: National inference and research cluster: capex | C4: From compute planner | D4: 3179880 | E4: 2119920 | F4: 0 | G4: 0 | H4: 0 | I4: =SUM(D4:H4)
A5: Compute | B5: National inference and research cluster: opex | C5: From compute planner | D5: 237645 | E5: 950580 | F5: 950580 | G5: 950580 | H5: 950580 | I5: =SUM(D5:H5)
A6: Compute | B6: Compute access credits | C6: Researchers and startups | D6: 300000 | E6: 500000 | F6: 700000 | G6: 800000 | H6: 800000 | I6: =SUM(D6:H6)
A7: Data | B7: Register digitisation | C7: Priority registers first | D7: 1500000 | E7: 2000000 | F7: 2000000 | G7: 1500000 | H7: 1000000 | I7: =SUM(D7:H7)
A8: Data | B8: Data exchange layer expansion | C8: Connect 20 more bodies | D8: 800000 | E8: 800000 | F8: 600000 | G8: 400000 | H8: 400000 | I8: =SUM(D8:H8)
A9: Data | B9: Language and speech corpora | C9: Community-led collection | D9: 400000 | E9: 600000 | F9: 600000 | G9: 400000 | H9: 300000 | I9: =SUM(D9:H9)
A10: Talent | B10: Civil-service AI curriculum | C10: Role-based, 3 tiers | D10: 500000 | E10: 800000 | F10: 900000 | G10: 900000 | H10: 800000 | I10: =SUM(D10:H10)
A11: Talent | B11: Scholarships and fellowships | C11: MSc/PhD with return bond | D11: 1000000 | E11: 1500000 | F11: 2000000 | G11: 2000000 | H11: 2000000 | I11: =SUM(D11:H11)
A12: Talent | B12: Research chairs and retention | C12: 6 chairs from Y2 | D12: 0 | E12: 600000 | F12: 600000 | G12: 600000 | H12: 600000 | I12: =SUM(D12:H12)
A13: Regulation | B13: Regulator AI unit | C13: 6-10 staff | D13: 400000 | E13: 500000 | F13: 600000 | G13: 600000 | H13: 600000 | I13: =SUM(D13:H13)
... A18: Monitoring and evaluation | B18: Independent evaluations | C18: Mid-term Y3, final Y5 | D18: 0 | E18: 0 | F18: 300000 | G18: 0 | H18: 400000 | I18: =SUM(D18:H18)

Sheet Financing shares
A1: Pillar | B1: National budget | C1: DFI loans | D1: Grants | E1: PPP and private | F1: Vendor credits | G1: Check (must be 100%)
A2: Governance and delivery unit | B2: 1 | C2: 0 | D2: 0 | E2: 0 | F2: 0 | G2: =SUM(B2:F2)
A3: Compute | B3: 0.3 | C3: 0.4 | D3: 0 | E3: 0.2 | F3: 0.1 | G3: =SUM(B3:F3)
A4: Data | B4: 0.4 | C4: 0.4 | D4: 0.2 | E4: 0 | F4: 0 | G4: =SUM(B4:F4)
A5: Talent | B5: 0.5 | C5: 0.1 | D5: 0.3 | E5: 0.1 | F5: 0 | G5: =SUM(B5:F5)
A6: Regulation | B6: 0.7 | C6: 0 | D6: 0.3 | E6: 0 | F6: 0 | G6: =SUM(B6:F6)
A7: Adoption and procurement | B7: 0.5 | C7: 0.3 | D7: 0.1 | E7: 0.1 | F7: 0 | G7: =SUM(B7:F7)
A8: Monitoring and evaluation | B8: 0.6 | C8: 0 | D8: 0.4 | E8: 0 | F8: 0 | G8: =SUM(B8:F8)

Sheet By pillar
A1: Pillar | B1: Y1 | C1: Y2 | D1: Y3 | E1: Y4 | F1: Y5 | G1: Total
A2: Governance and delivery unit | B2: =SUMIFS('Line items'!D$2:D$18,'Line items'!$A$2:$A$18,$A2) | C2: =SUMIFS('Line items'!E$2:E$18,'Line items'!$A$2:$A$18,$A2) | D2: =SUMIFS('Line items'!F$2:F$18,'Line items'!$A$2:$A$18,$A2) | E2: =SUMIFS('Line items'!G$2:G$18,'Line items'!$A$2:$A$18,$A2) | F2: =SUMIFS('Line items'!H$2:H$18,'Line items'!$A$2:$A$18,$A2) | G2: =SUM(B2:F2)
A3: Compute | B3: =SUMIFS('Line items'!D$2:D$18,'Line items'!$A$2:$A$18,$A3) | C3: =SUMIFS('Line items'!E$2:E$18,'Line items'!$A$2:$A$18,$A3) | D3: =SUMIFS('Line items'!F$2:F$18,'Line items'!$A$2:$A$18,$A3) | E3: =SUMIFS('Line items'!G$2:G$18,'Line items'!$A$2:$A$18,$A3) | F3: =SUMIFS('Line items'!H$2:H$18,'Line items'!$A$2:$A$18,$A3) | G3: =SUM(B3:F3)
A4: Data | B4: =SUMIFS('Line items'!D$2:D$18,'Line items'!$A$2:$A$18,$A4) | C4: =SUMIFS('Line items'!E$2:E$18,'Line items'!$A$2:$A$18,$A4) | D4: =SUMIFS('Line items'!F$2:F$18,'Line items'!$A$2:$A$18,$A4) | E4: =SUMIFS('Line items'!G$2:G$18,'Line items'!$A$2:$A$18,$A4) | F4: =SUMIFS('Line items'!H$2:H$18,'Line items'!$A$2:$A$18,$A4) | G4: =SUM(B4:F4)
A5: Talent | B5: =SUMIFS('Line items'!D$2:D$18,'Line items'!$A$2:$A$18,$A5) | C5: =SUMIFS('Line items'!E$2:E$18,'Line items'!$A$2:$A$18,$A5) | D5: =SUMIFS('Line items'!F$2:F$18,'Line items'!$A$2:$A$18,$A5) | E5: =SUMIFS('Line items'!G$2:G$18,'Line items'!$A$2:$A$18,$A5) | F5: =SUMIFS('Line items'!H$2:H$18,'Line items'!$A$2:$A$18,$A5) | G5: =SUM(B5:F5)
A6: Regulation | B6: =SUMIFS('Line items'!D$2:D$18,'Line items'!$A$2:$A$18,$A6) | C6: =SUMIFS('Line items'!E$2:E$18,'Line items'!$A$2:$A$18,$A6) | D6: =SUMIFS('Line items'!F$2:F$18,'Line items'!$A$2:$A$18,$A6) | E6: =SUMIFS('Line items'!G$2:G$18,'Line items'!$A$2:$A$18,$A6) | F6: =SUMIFS('Line items'!H$2:H$18,'Line items'!$A$2:$A$18,$A6) | G6: =SUM(B6:F6)
A7: Adoption and procurement | B7: =SUMIFS('Line items'!D$2:D$18,'Line items'!$A$2:$A$18,$A7) | C7: =SUMIFS('Line items'!E$2:E$18,'Line items'!$A$2:$A$18,$A7) | D7: =SUMIFS('Line items'!F$2:F$18,'Line items'!$A$2:$A$18,$A7) | E7: =SUMIFS('Line items'!G$2:G$18,'Line items'!$A$2:$A$18,$A7) | F7: =SUMIFS('Line items'!H$2:H$18,'Line items'!$A$2:$A$18,$A7) | G7: =SUM(B7:F7)
A8: Monitoring and evaluation | B8: =SUMIFS('Line items'!D$2:D$18,'Line items'!$A$2:$A$18,$A8) | C8: =SUMIFS('Line items'!E$2:E$18,'Line items'!$A$2:$A$18,$A8) | D8: =SUMIFS('Line items'!F$2:F$18,'Line items'!$A$2:$A$18,$A8) | E8: =SUMIFS('Line items'!G$2:G$18,'Line items'!$A$2:$A$18,$A8) | F8: =SUMIFS('Line items'!H$2:H$18,'Line items'!$A$2:$A$18,$A8) | G8: =SUM(B8:F8)
A9: Total | B9: =SUM(B2:B8) | C9: =SUM(C2:C8) | D9: =SUM(D2:D8) | E9: =SUM(E2:E8) | F9: =SUM(F2:F8) | G9: =SUM(G2:G8)

Sheet By source
A1: Source | B1: Y1 | C1: Y2 | D1: Y3 | E1: Y4 | F1: Y5 | G1: Total
A2: National budget | B2: =SUMPRODUCT('By pillar'!B$2:B$8,'Financing shares'!B$2:B$8) | C2: =SUMPRODUCT('By pillar'!C$2:C$8,'Financing shares'!B$2:B$8) | D2: =SUMPRODUCT('By pillar'!D$2:D$8,'Financing shares'!B$2:B$8) | E2: =SUMPRODUCT('By pillar'!E$2:E$8,'Financing shares'!B$2:B$8) | F2: =SUMPRODUCT('By pillar'!F$2:F$8,'Financing shares'!B$2:B$8) | G2: =SUM(B2:F2)
A3: DFI loans | B3: =SUMPRODUCT('By pillar'!B$2:B$8,'Financing shares'!C$2:C$8) | C3: =SUMPRODUCT('By pillar'!C$2:C$8,'Financing shares'!C$2:C$8) | D3: =SUMPRODUCT('By pillar'!D$2:D$8,'Financing shares'!C$2:C$8) | E3: =SUMPRODUCT('By pillar'!E$2:E$8,'Financing shares'!C$2:C$8) | F3: =SUMPRODUCT('By pillar'!F$2:F$8,'Financing shares'!C$2:C$8) | G3: =SUM(B3:F3)
A4: Grants | B4: =SUMPRODUCT('By pillar'!B$2:B$8,'Financing shares'!D$2:D$8) | C4: =SUMPRODUCT('By pillar'!C$2:C$8,'Financing shares'!D$2:D$8) | D4: =SUMPRODUCT('By pillar'!D$2:D$8,'Financing shares'!D$2:D$8) | E4: =SUMPRODUCT('By pillar'!E$2:E$8,'Financing shares'!D$2:D$8) | F4: =SUMPRODUCT('By pillar'!F$2:F$8,'Financing shares'!D$2:D$8) | G4: =SUM(B4:F4)
A5: PPP and private | B5: =SUMPRODUCT('By pillar'!B$2:B$8,'Financing shares'!E$2:E$8) | C5: =SUMPRODUCT('By pillar'!C$2:C$8,'Financing shares'!E$2:E$8) | D5: =SUMPRODUCT('By pillar'!D$2:D$8,'Financing shares'!E$2:E$8) | E5: =SUMPRODUCT('By pillar'!E$2:E$8,'Financing shares'!E$2:E$8) | F5: =SUMPRODUCT('By pillar'!F$2:F$8,'Financing shares'!E$2:E$8) | G5: =SUM(B5:F5)
A6: Vendor credits | B6: =SUMPRODUCT('By pillar'!B$2:B$8,'Financing shares'!F$2:F$8) | C6: =SUMPRODUCT('By pillar'!C$2:C$8,'Financing shares'!F$2:F$8) | D6: =SUMPRODUCT('By pillar'!D$2:D$8,'Financing shares'!F$2:F$8) | E6: =SUMPRODUCT('By pillar'!E$2:E$8,'Financing shares'!F$2:F$8) | F6: =SUMPRODUCT('By pillar'!F$2:F$8,'Financing shares'!F$2:F$8) | G6: =SUM(B6:F6)
A7: Total | B7: =SUM(B2:B6) | C7: =SUM(C2:C6) | D7: =SUM(D2:D6) | E7: =SUM(E2:E6) | F7: =SUM(F2:F6) | G7: =SUM(G2:G6)

Sheet Summary
A1: Five-year total by pillar | B1: USD | C1: Share
A2: Governance and delivery unit | B2: ='By pillar'!G2 | C2: =B2/'By pillar'!G9
A3: Compute | B3: ='By pillar'!G3 | C3: =B3/'By pillar'!G9
A4: Data | B4: ='By pillar'!G4 | C4: =B4/'By pillar'!G9
A5: Talent | B5: ='By pillar'!G5 | C5: =B5/'By pillar'!G9
A6: Regulation | B6: ='By pillar'!G6 | C6: =B6/'By pillar'!G9
A7: Adoption and procurement | B7: ='By pillar'!G7 | C7: =B7/'By pillar'!G9
A8: Monitoring and evaluation | B8: ='By pillar'!G8 | C8: =B8/'By pillar'!G9
A9: Total | B9: ='By pillar'!G9 | C9: =SUM(C2:C8)
A11: Five-year total by source
A12: National budget | B12: ='By source'!G2 | C12: =B12/'By source'!G7
A13: DFI loans | B13: ='By source'!G3 | C13: =B13/'By source'!G7
A14: Grants | B14: ='By source'!G4 | C14: =B14/'By source'!G7
A15: PPP and private | B15: ='By source'!G5 | C15: =B15/'By source'!G7
A16: Vendor credits | B16: ='By source'!G6 | C16: =B16/'By source'!G7
A18: Check: pillars minus sources (must be 0) | B18: =ROUND('By pillar'!G9-'By source'!G7,0)
